flake8_local_import/__init__.py
flake8_local_import/constants.py
flake8_local_import/plugin.py
flake8_local_import-1.0.6.dist-info/LICENSE
flake8_local_import-1.0.6.dist-info/METADATA
flake8_local_import-1.0.6.dist-info/WHEEL
flake8_local_import-1.0.6.dist-info/entry_points.txt
flake8_local_import-1.0.6.dist-info/top_level.txt
flake8_local_import-1.0.6.dist-info/RECORD
