Metadata-Version: 2.1
Name: flake8-local-import
Version: 1.0.6
Summary: Python 3 check local import for flake8
Home-page: https://github.com/meanmail-dev/flake8-local-import
Author: meanmail
Author-email: meanmail@meanmail.dev
License: MIT
Platform: UNKNOWN
Classifier: Framework :: Flake8
Classifier: Environment :: Console
Classifier: Intended Audience :: Developers
Classifier: License :: OSI Approved :: MIT License
Classifier: Programming Language :: Python
Classifier: Programming Language :: Python :: 3
Classifier: Topic :: Software Development :: Libraries :: Python Modules
Classifier: Topic :: Software Development :: Quality Assurance
License-File: LICENSE
Requires-Dist: flake8 (>3.0.0)
Requires-Dist: flake8-plugin-utils (~=1.3.2)
